{"cameraMode":{"drawMode":0,"name":"Shaded","section":"Shading Mode"},"sceneLighting":true,"audioPlay":false,"sceneViewState":{"m_AlwaysRefresh":false,"showFog":true,"showSkybox":true,"showFlares":true,"showImageEffects":true,"showParticleSystems":true,"showVisualEffectGraphs":true,"m_FxEnabled":true},"in2DMode":false,"pivot":{"x":1.0111165046691895,"y":6.872117042541504,"z":3.461239814758301},"rotation":{"x":-0.04975016787648201,"y":-0.039843179285526279,"z":0.001988448901101947,"w":-0.99797523021698},"size":37.19990539550781,"orthographic":false}