{"cameraMode":{"drawMode":0,"name":"Shaded","section":"Shading Mode"},"sceneLighting":true,"audioPlay":false,"sceneViewState":{"m_AlwaysRefresh":false,"showFog":true,"showSkybox":true,"showFlares":true,"showImageEffects":true,"showParticleSystems":true,"showVisualEffectGraphs":true,"m_FxEnabled":false},"in2DMode":false,"pivot":{"x":131.18565368652345,"y":4.929447174072266,"z":780.2435302734375},"rotation":{"x":-0.29613393545150759,"y":-0.6860084533691406,"z":0.3663484454154968,"w":-0.5545225739479065},"size":21.541311264038087,"orthographic":false}