{"cameraMode":{"drawMode":0,"name":"Shaded","section":"Shading Mode"},"sceneLighting":true,"audioPlay":false,"sceneViewState":{"m_AlwaysRefresh":false,"showFog":true,"showSkybox":true,"showFlares":true,"showImageEffects":true,"showParticleSystems":true,"showVisualEffectGraphs":true,"m_FxEnabled":true},"in2DMode":false,"pivot":{"x":104.31668090820313,"y":9.278151512145996,"z":816.8240356445313},"rotation":{"x":0.31304189562797549,"y":0.6440207958221436,"z":-0.32686686515808108,"w":0.6167762279510498},"size":6.775997161865234,"orthographic":false}