{"cameraMode":{"drawMode":0,"name":"Shaded","section":"Shading Mode"},"sceneLighting":true,"audioPlay":false,"sceneViewState":{"m_AlwaysRefresh":false,"showFog":true,"showSkybox":true,"showFlares":true,"showImageEffects":true,"showParticleSystems":true,"showVisualEffectGraphs":true,"m_FxEnabled":true},"in2DMode":false,"pivot":{"x":162.8157958984375,"y":6.1194682121276859,"z":771.6736450195313},"rotation":{"x":-0.1932590901851654,"y":-0.3141719102859497,"z":0.06549278646707535,"w":-0.9271795153617859},"size":11.677644729614258,"orthographic":false}